.coveragerc
.travis.yml
AUTHORS
CHANGES
CONTRIBUTING.rst
LICENSE
MANIFEST.in
README.rst
RELEASE-NOTES.rst
run-tests.sh
setup.cfg
setup.py
tox.ini
Flask_RateLimiter.egg-info/PKG-INFO
Flask_RateLimiter.egg-info/SOURCES.txt
Flask_RateLimiter.egg-info/dependency_links.txt
Flask_RateLimiter.egg-info/not-zip-safe
Flask_RateLimiter.egg-info/requires.txt
Flask_RateLimiter.egg-info/top_level.txt
docs/Makefile
docs/conf.py
docs/index.rst
docs/_templates/sidebarintro.html
docs/_themes/README
docs/_themes/flask_theme_support.py
docs/_themes/flask/layout.html
docs/_themes/flask/relations.html
docs/_themes/flask/theme.conf
docs/_themes/flask/static/flasky.css_t
docs/_themes/flask_small/layout.html
docs/_themes/flask_small/theme.conf
docs/_themes/flask_small/static/flasky.css_t
flask_ratelimiter/__init__.py
flask_ratelimiter/version.py
flask_ratelimiter/backends/__init__.py
flask_ratelimiter/backends/backend.py
flask_ratelimiter/backends/flaskcacheredis_backend.py
flask_ratelimiter/backends/simpleredis_backend.py
tests/__init__.py
tests/helpers.py
tests/test_backends.py
tests/test_core.py
tests/test_ext.py